{
  "schemaVersion": "dataset_page.v1",
  "part": 3,
  "page": 15,
  "pageId": "page_0015",
  "source": {
    "pdfPath": "docs/ufo3.pdf",
    "sha256": "9a3db3235a87e685beaa3157957308074b7bfca707f92742f177cdf7b68e2c5d"
  },
  "sourceLayer": "line_audit",
  "translationReadiness": "partial_ready",
  "pageType": "low_quality_or_mixed_document",
  "pageRecommendation": "DENSE_PAGE_REQUIRES_CROP_LINE_AUDIT",
  "pageReadinessNote": "16 permanent_unresolved line(s) excluded under SRC-896. 25 IMAGE_MATCHED line(s) eligible for handoff.",
  "excludedLineIds": [
    "page_0015-l0001",
    "page_0015-l0002",
    "page_0015-l0020",
    "page_0015-l0021",
    "page_0015-l0022",
    "page_0015-l0026",
    "page_0015-l0030",
    "page_0015-l0031",
    "page_0015-l0032",
    "page_0015-l0033",
    "page_0015-l0034",
    "page_0015-l0036",
    "page_0015-l0037",
    "page_0015-l0039",
    "page_0015-l0043",
    "page_0015-l0044"
  ],
  "lineCount": 46,
  "lines": [
    {
      "lineNumber": 1,
      "text": "U.S. DEPARTMENT OF JUSTICE",
      "status": "permanent_unresolved",
      "unresolvedReason": "other_documented"
    },
    {
      "lineNumber": 2,
      "text": "COMMUNICATIONS SECTION",
      "status": "permanent_unresolved",
      "unresolvedReason": "other_documented"
    },
    {
      "lineNumber": 3,
      "text": "AUG 12 1947",
      "status": "image_matched"
    },
    {
      "lineNumber": 4,
      "status": "blank"
    },
    {
      "lineNumber": 5,
      "text": "TELETYPE",
      "status": "image_matched"
    },
    {
      "lineNumber": 6,
      "status": "blank"
    },
    {
      "lineNumber": 7,
      "text": "Mr. Tolson",
      "status": "image_matched"
    },
    {
      "lineNumber": 8,
      "text": "Mr. E. A. Tamm",
      "status": "image_matched"
    },
    {
      "lineNumber": 9,
      "text": "Mr. Clegg",
      "status": "image_matched"
    },
    {
      "lineNumber": 10,
      "text": "Mr. Glavin",
      "status": "image_matched"
    },
    {
      "lineNumber": 11,
      "text": "Mr. Ladd",
      "status": "image_matched"
    },
    {
      "lineNumber": 12,
      "text": "Mr. Nichols",
      "status": "image_matched"
    },
    {
      "lineNumber": 13,
      "text": "Mr. Rosen",
      "status": "image_matched"
    },
    {
      "lineNumber": 14,
      "text": "Mr. Tracy",
      "status": "image_matched"
    },
    {
      "lineNumber": 15,
      "text": "Mr. Egan",
      "status": "image_matched"
    },
    {
      "lineNumber": 16,
      "text": "Mr. Gurnea",
      "status": "image_matched"
    },
    {
      "lineNumber": 17,
      "text": "KLS Mr. Harbo",
      "status": "image_matched"
    },
    {
      "lineNumber": 18,
      "text": "Mr. Mohr",
      "status": "image_matched"
    },
    {
      "lineNumber": 19,
      "text": "Mr. Pennington",
      "status": "image_matched"
    },
    {
      "lineNumber": 20,
      "text": "Mr. [unclear] Tamm",
      "status": "permanent_unresolved",
      "unresolvedReason": "other_documented"
    },
    {
      "lineNumber": 21,
      "text": "Tele. Room",
      "status": "permanent_unresolved",
      "unresolvedReason": "other_documented"
    },
    {
      "lineNumber": 22,
      "text": "Miss Gandy",
      "status": "permanent_unresolved",
      "unresolvedReason": "other_documented"
    },
    {
      "lineNumber": 23,
      "status": "blank"
    },
    {
      "lineNumber": 24,
      "text": "FBI SEATTLE",
      "status": "image_matched"
    },
    {
      "lineNumber": 25,
      "text": "8-12-47",
      "status": "image_matched"
    },
    {
      "lineNumber": 26,
      "text": "[unclear]05 PM PST",
      "status": "permanent_unresolved",
      "unresolvedReason": "other_documented"
    },
    {
      "lineNumber": 27,
      "text": "DIRECTOR AND SACS CHICAGO AND BUTTE",
      "status": "image_matched"
    },
    {
      "lineNumber": 28,
      "text": "URGENT",
      "status": "image_matched"
    },
    {
      "lineNumber": 29,
      "status": "blank"
    },
    {
      "lineNumber": 30,
      "text": "FLYING DISCS SIGHTED BY [REDACTED] AND [REDACTED], TACOMA, WN.,",
      "status": "permanent_unresolved",
      "unresolvedReason": "other_documented"
    },
    {
      "lineNumber": 31,
      "text": "SM DASH X . REMYTEL AUGUST SEVEN LAST. [REDACTED] UNITED AIRLINES",
      "status": "permanent_unresolved",
      "unresolvedReason": "other_documented"
    },
    {
      "lineNumber": 32,
      "text": "PILOT, INTERVIEWED RE ASSOCIATIONS WITH [REDACTED]",
      "status": "permanent_unresolved",
      "unresolvedReason": "other_documented"
    },
    {
      "lineNumber": 33,
      "text": "AND [REDACTED] IN TACOMA, WN., FROM JULY THIRTYONE TO AUGUST THIRD",
      "status": "permanent_unresolved",
      "unresolvedReason": "other_documented"
    },
    {
      "lineNumber": 34,
      "text": "LAST. [REDACTED] HAS RECEIVED PREVIOUS PUBLICITY FOR HAVING SEEN FLYING",
      "status": "permanent_unresolved",
      "unresolvedReason": "other_documented"
    },
    {
      "lineNumber": 35,
      "text": "DISCS OR SIMILAR OBJECTS ON JULY FOURTH LAST IN COMPANY WITH HIS CO-",
      "status": "image_matched"
    },
    {
      "lineNumber": 36,
      "text": "PILOT, [REDACTED] DURING ROUTENE UNITED AIRLINES FLIGHT OUT OF",
      "status": "permanent_unresolved",
      "unresolvedReason": "other_documented"
    },
    {
      "lineNumber": 37,
      "text": "BOISE, IDAHO. [REDACTED] RELATES THAT HE WENT TO TACOMA, WN., FROM SEATTLE",
      "status": "permanent_unresolved",
      "unresolvedReason": "other_documented"
    },
    {
      "lineNumber": 38,
      "text": "ON THURSDAY, JULY THIRTYONE LAST IN RESPONSE TO TELEPHONE CALL FROM",
      "status": "image_matched"
    },
    {
      "lineNumber": 39,
      "text": "[REDACTED] AT TACOMA. [REDACTED] CLAIMS HE HAD PREVIOUSLY MET ARNOLD",
      "status": "permanent_unresolved",
      "unresolvedReason": "other_documented"
    },
    {
      "lineNumber": 40,
      "text": "ON TWO OCCASIONS, THE FIRST TIME ON JULY FIFTH LAST IN OFFICES OF",
      "status": "image_matched"
    },
    {
      "lineNumber": 41,
      "text": "SEATTLE POST- INTELLIGENCER WHERE BOTH WERE INTERVIEWED RE FLYING DISCS",
      "status": "image_matched"
    },
    {
      "lineNumber": 42,
      "text": "THEY HAD SEEN, AND ON SECOND OCCASION IN BOISE, IDAHO, ABOUT THREE",
      "status": "image_matched"
    },
    {
      "lineNumber": 43,
      "text": "WEEKS AGO WHILE HE, [REDACTED] WAS PASSING THROUGH ON ROUTINE FLIGHT. ON",
      "status": "permanent_unresolved",
      "unresolvedReason": "other_documented"
    },
    {
      "lineNumber": 44,
      "text": "THIS LATTER OCCASION, [REDACTED] WAS IN COMPANY OF [REDACTED]",
      "status": "permanent_unresolved",
      "unresolvedReason": "other_documented"
    },
    {
      "lineNumber": 45,
      "status": "blank"
    },
    {
      "lineNumber": 46,
      "text": "57",
      "status": "image_matched"
    }
  ],
  "blockCount": null
}
