{
  "schemaVersion": "dataset_page.v1",
  "part": 11,
  "page": 104,
  "pageId": "page_0104",
  "source": {
    "pdfPath": "docs/ufo11.pdf",
    "sha256": "33ebbb1824507dd319b4f668003dfd4bf9aebd5b80c894f2eb466e2c25477c4b"
  },
  "sourceLayer": "line_audit",
  "translationReadiness": "ready",
  "pageType": "low_quality_or_mixed_document",
  "pageRecommendation": "DENSE_PAGE_REQUIRES_CROP_LINE_AUDIT",
  "pageReadinessNote": "All 30 source-bearing line(s) IMAGE_MATCHED. Ready for translation handoff.",
  "excludedLineIds": [],
  "lineCount": 32,
  "lines": [
    {
      "lineNumber": 1,
      "text": "The",
      "status": "image_matched"
    },
    {
      "lineNumber": 2,
      "text": "Little",
      "status": "image_matched"
    },
    {
      "lineNumber": 3,
      "text": "Man",
      "status": "image_matched"
    },
    {
      "lineNumber": 4,
      "text": "Who",
      "status": "image_matched"
    },
    {
      "lineNumber": 5,
      "text": "Wasn't",
      "status": "image_matched"
    },
    {
      "lineNumber": 6,
      "status": "blank"
    },
    {
      "lineNumber": 7,
      "text": "Edward Watters",
      "status": "image_matched"
    },
    {
      "lineNumber": 8,
      "text": "and two friends",
      "status": "image_matched"
    },
    {
      "lineNumber": 9,
      "text": "said they saw",
      "status": "image_matched"
    },
    {
      "lineNumber": 10,
      "text": "a flying saucer",
      "status": "image_matched"
    },
    {
      "lineNumber": 11,
      "text": "on U. S. High-",
      "status": "image_matched"
    },
    {
      "lineNumber": 12,
      "text": "way 78 near",
      "status": "image_matched"
    },
    {
      "lineNumber": 13,
      "text": "Atlanta, Ga., and",
      "status": "image_matched"
    },
    {
      "lineNumber": 14,
      "text": "several small",
      "status": "image_matched"
    },
    {
      "lineNumber": 15,
      "text": "creatures running",
      "status": "image_matched"
    },
    {
      "lineNumber": 16,
      "text": "toward it. They",
      "status": "image_matched"
    },
    {
      "lineNumber": 17,
      "text": "ran over one",
      "status": "image_matched"
    },
    {
      "lineNumber": 18,
      "text": "but the others",
      "status": "image_matched"
    },
    {
      "lineNumber": 19,
      "text": "entered the sau-",
      "status": "image_matched"
    },
    {
      "lineNumber": 20,
      "text": "cer and flew off",
      "status": "image_matched"
    },
    {
      "lineNumber": 21,
      "text": "in a blaze of",
      "status": "image_matched"
    },
    {
      "lineNumber": 22,
      "text": "light. Mr. Wat-",
      "status": "image_matched"
    },
    {
      "lineNumber": 23,
      "text": "ters exhibits",
      "status": "image_matched"
    },
    {
      "lineNumber": 24,
      "text": "the \"man from",
      "status": "image_matched"
    },
    {
      "lineNumber": 25,
      "text": "Mars\" but an",
      "status": "image_matched"
    },
    {
      "lineNumber": 26,
      "text": "anatomy pro-",
      "status": "image_matched"
    },
    {
      "lineNumber": 27,
      "text": "fessor called it",
      "status": "image_matched"
    },
    {
      "lineNumber": 28,
      "text": "a skinned",
      "status": "image_matched"
    },
    {
      "lineNumber": 29,
      "text": "monkey.",
      "status": "image_matched"
    },
    {
      "lineNumber": 30,
      "status": "blank"
    },
    {
      "lineNumber": 31,
      "text": "ENCLOSURE 62-3411-334",
      "status": "image_matched"
    },
    {
      "lineNumber": 32,
      "text": "Washington Daily News 7/9/53",
      "status": "image_matched"
    }
  ],
  "blockCount": null
}
