{
  "schemaVersion": "dataset_page.v1",
  "part": 8,
  "page": 9,
  "pageId": "page_0009",
  "source": {
    "pdfPath": "docs/ufo8.pdf",
    "sha256": "9c50bf6138108cd841924260f9d520e2f4d6c46b7ca822d99dc52c12c7d8b933"
  },
  "sourceLayer": "line_audit",
  "translationReadiness": "not_ready",
  "pageType": "low_quality_or_mixed_document",
  "pageRecommendation": "READY_FOR_LINE_AUDIT",
  "pageReadinessNote": null,
  "excludedLineIds": [],
  "lineCount": 12,
  "lines": [
    {
      "lineNumber": 1,
      "text": "in his Buffalo office. The story is to long to write it down to-day",
      "status": "pending_image_audit"
    },
    {
      "lineNumber": 2,
      "text": "feel jittery about this fellow Ubalsty as I think he is a very bad egg",
      "status": "pending_image_audit"
    },
    {
      "lineNumber": 3,
      "text": "etc. He was friendly to me and told me to do the best I could and when",
      "status": "pending_image_audit"
    },
    {
      "lineNumber": 4,
      "text": "at it day to let them know and my price will be paid pronto.",
      "status": "pending_image_audit"
    },
    {
      "lineNumber": 5,
      "text": "This keeps me on a footing with them and I stall them off all the time.",
      "status": "pending_image_audit"
    },
    {
      "lineNumber": 6,
      "text": "Well this is the saucer as I have it for you.",
      "status": "pending_image_audit"
    },
    {
      "lineNumber": 7,
      "status": "blank"
    },
    {
      "lineNumber": 8,
      "text": "Yours Truly",
      "status": "image_matched"
    },
    {
      "lineNumber": 9,
      "text": "[REDACTED]",
      "status": "redaction_marker_check"
    },
    {
      "lineNumber": 10,
      "text": "[REDACTED]",
      "status": "redaction_marker_check"
    },
    {
      "lineNumber": 11,
      "text": "yuba city",
      "status": "image_matched"
    },
    {
      "lineNumber": 12,
      "text": "calif.",
      "status": "image_matched"
    }
  ],
  "blockCount": null
}
