{
  "schemaVersion": "dataset_page.v1",
  "part": 13,
  "page": 29,
  "pageId": "page_0029",
  "source": {
    "pdfPath": "docs/ufo13.pdf",
    "sha256": "423b23b3741786f13d58b5dbd2c23eb0f6081fc406fc35482c621baef44b50aa"
  },
  "sourceLayer": "line_audit",
  "translationReadiness": "not_ready",
  "pageType": "low_quality_or_mixed_document",
  "pageRecommendation": "DENSE_PAGE_REQUIRES_CROP_LINE_AUDIT",
  "pageReadinessNote": null,
  "excludedLineIds": [],
  "lineCount": 38,
  "lines": [
    {
      "lineNumber": 1,
      "text": "Director, FBI",
      "status": "image_matched"
    },
    {
      "lineNumber": 2,
      "text": "RE: DETROIT FLYING SAUCER CLUB",
      "status": "image_matched"
    },
    {
      "lineNumber": 3,
      "text": "ESPIONAGE - X",
      "status": "pending_image_audit"
    },
    {
      "lineNumber": 4,
      "status": "blank"
    },
    {
      "lineNumber": 5,
      "text": "3. A saucer landed at 4:30 a.m., September 30,",
      "status": "image_matched"
    },
    {
      "lineNumber": 6,
      "text": "1954, at Rotunda Drive and Southfield (Detroit)",
      "status": "image_matched"
    },
    {
      "lineNumber": 7,
      "text": "with strange greenish men in brown uniforms.",
      "status": "image_matched"
    },
    {
      "lineNumber": 8,
      "status": "blank"
    },
    {
      "lineNumber": 9,
      "text": "4. Unseen psychic forces (no further explanation.)",
      "status": "image_matched"
    },
    {
      "lineNumber": 10,
      "status": "blank"
    },
    {
      "lineNumber": 11,
      "text": "[REDACTED]",
      "status": "redaction_marker_check"
    },
    {
      "lineNumber": 12,
      "text": "[REDACTED]",
      "status": "redaction_marker_check"
    },
    {
      "lineNumber": 13,
      "text": "[REDACTED]",
      "status": "redaction_marker_check"
    },
    {
      "lineNumber": 14,
      "text": "[REDACTED]",
      "status": "redaction_marker_check"
    },
    {
      "lineNumber": 15,
      "status": "blank"
    },
    {
      "lineNumber": 16,
      "text": "At this meeting, [REDACTED] said she was an athiest. The main",
      "status": "redaction_marker_check"
    },
    {
      "lineNumber": 17,
      "text": "discussion was about religion, science, and double talk, [REDACTED]",
      "status": "redaction_marker_check"
    },
    {
      "lineNumber": 18,
      "text": "said. Twenty such discussion groups exist. [REDACTED] said there would",
      "status": "redaction_marker_check"
    },
    {
      "lineNumber": 19,
      "text": "be landings in Detroit in October, but she could be wrong. Before",
      "status": "image_matched"
    },
    {
      "lineNumber": 20,
      "text": "the meeting started, [REDACTED] called, saying, she was not coming",
      "status": "redaction_marker_check"
    },
    {
      "lineNumber": 21,
      "text": "and was resigning.",
      "status": "image_matched"
    },
    {
      "lineNumber": 22,
      "status": "blank"
    },
    {
      "lineNumber": 23,
      "text": "[REDACTED]",
      "status": "redaction_marker_check"
    },
    {
      "lineNumber": 24,
      "text": "[REDACTED]",
      "status": "redaction_marker_check"
    },
    {
      "lineNumber": 25,
      "text": "[REDACTED]",
      "status": "redaction_marker_check"
    },
    {
      "lineNumber": 26,
      "text": "[REDACTED]",
      "status": "redaction_marker_check"
    },
    {
      "lineNumber": 27,
      "text": "[REDACTED]",
      "status": "redaction_marker_check"
    },
    {
      "lineNumber": 28,
      "text": "[REDACTED]",
      "status": "redaction_marker_check"
    },
    {
      "lineNumber": 29,
      "text": "[REDACTED]",
      "status": "redaction_marker_check"
    },
    {
      "lineNumber": 30,
      "text": "[REDACTED]",
      "status": "redaction_marker_check"
    },
    {
      "lineNumber": 31,
      "text": "[REDACTED]",
      "status": "redaction_marker_check"
    },
    {
      "lineNumber": 32,
      "status": "blank"
    },
    {
      "lineNumber": 33,
      "text": "[REDACTED] said the purpose of this leaders meeting was to discuss",
      "status": "redaction_marker_check"
    },
    {
      "lineNumber": 34,
      "text": "how to handle issues arising in group meetings. These were:",
      "status": "image_matched"
    },
    {
      "lineNumber": 35,
      "status": "blank"
    },
    {
      "lineNumber": 36,
      "text": "1. Religious",
      "status": "image_matched"
    },
    {
      "lineNumber": 37,
      "status": "blank"
    },
    {
      "lineNumber": 38,
      "text": "- 4 -",
      "status": "image_matched"
    }
  ],
  "blockCount": null
}
