{
  "schemaVersion": "dataset_page.v1",
  "part": 14,
  "page": 44,
  "pageId": "page_0044",
  "source": {
    "pdfPath": "docs/ufo14.pdf",
    "sha256": "db87b2051dc434188f23e59904c375d0b52b3692763d48ef6163a0f309554da3"
  },
  "sourceLayer": "line_audit",
  "translationReadiness": "partial_ready",
  "pageType": "low_quality_or_mixed_document",
  "pageRecommendation": "DENSE_PAGE_REQUIRES_CROP_LINE_AUDIT",
  "pageReadinessNote": "14 permanent_unresolved line(s) excluded under SRC-896. 32 IMAGE_MATCHED line(s) eligible for handoff.",
  "excludedLineIds": [
    "page_0044-l0001",
    "page_0044-l0003",
    "page_0044-l0008",
    "page_0044-l0009",
    "page_0044-l0021",
    "page_0044-l0025",
    "page_0044-l0026",
    "page_0044-l0027",
    "page_0044-l0028",
    "page_0044-l0032",
    "page_0044-l0037",
    "page_0044-l0039",
    "page_0044-l0040",
    "page_0044-l0047"
  ],
  "lineCount": 48,
  "lines": [
    {
      "lineNumber": 1,
      "text": "Office Memorandum • UNITED [REDACTED]NMENT",
      "status": "permanent_unresolved",
      "unresolvedReason": "other_documented"
    },
    {
      "lineNumber": 2,
      "text": "TO : DIRECTOR, FBI DATE: 12/19/58",
      "status": "image_matched"
    },
    {
      "lineNumber": 3,
      "text": "FROM : SAC, PHOENIX (52-667) FLYING DISCS",
      "status": "permanent_unresolved",
      "unresolvedReason": "other_documented"
    },
    {
      "lineNumber": 4,
      "text": "SUBJECT: MISCELLANEOUS - INFORMATION CONCERNING",
      "status": "image_matched"
    },
    {
      "lineNumber": 5,
      "text": "(Nationalities Intelligence)",
      "status": "image_matched"
    },
    {
      "lineNumber": 6,
      "text": "Re Bureau letter 12/16/58.",
      "status": "image_matched"
    },
    {
      "lineNumber": 7,
      "text": "COLO",
      "status": "image_matched"
    },
    {
      "lineNumber": 8,
      "text": "On 12/19/58, [REDACTED] Scottsdale, Arizona, stated to SAS [REDACTED]",
      "status": "permanent_unresolved",
      "unresolvedReason": "other_documented"
    },
    {
      "lineNumber": 9,
      "text": "[REDACTED] that he had a hobby",
      "status": "permanent_unresolved",
      "unresolvedReason": "other_documented"
    },
    {
      "lineNumber": 10,
      "text": "of gathering information concerning flying saucers and",
      "status": "image_matched"
    },
    {
      "lineNumber": 11,
      "text": "also gathering information concerning mysteries of the",
      "status": "image_matched"
    },
    {
      "lineNumber": 12,
      "text": "sea. He stated that any literature written he obtains",
      "status": "image_matched"
    },
    {
      "lineNumber": 13,
      "text": "in order to pursue this hobby. He referred agents to",
      "status": "image_matched"
    },
    {
      "lineNumber": 14,
      "text": "books written by Major DONALD E. KEYHOE entitled",
      "status": "image_matched"
    },
    {
      "lineNumber": 15,
      "text": "\"Flying Saucers from Outer Space\" and a book entitled",
      "status": "image_matched"
    },
    {
      "lineNumber": 16,
      "text": "\"Flying Saucers Conspiracy.\" Both of these books were",
      "status": "image_matched"
    },
    {
      "lineNumber": 17,
      "text": "published by Henry Holt Company, 383 Madison, New York, 17,",
      "status": "image_matched"
    },
    {
      "lineNumber": 18,
      "text": "New York. Major KEYHOE is a retired Major of the U. S.",
      "status": "image_matched"
    },
    {
      "lineNumber": 19,
      "text": "Marine Corps.",
      "status": "image_matched"
    },
    {
      "lineNumber": 20,
      "status": "blank"
    },
    {
      "lineNumber": 21,
      "text": "Concerning the [REDACTED], he referred agents to",
      "status": "permanent_unresolved",
      "unresolvedReason": "other_documented"
    },
    {
      "lineNumber": 22,
      "text": "the book entitled \"They Knew Too Much About Flying",
      "status": "image_matched"
    },
    {
      "lineNumber": 23,
      "text": "Saucers\", written by GRAY BARKER and published by",
      "status": "image_matched"
    },
    {
      "lineNumber": 24,
      "text": "University Books Publisher, April, 1956, third",
      "status": "image_matched"
    },
    {
      "lineNumber": 25,
      "text": "printing June, 1956. According to [REDACTED]",
      "status": "permanent_unresolved",
      "unresolvedReason": "other_documented"
    },
    {
      "lineNumber": 26,
      "text": "resides at Clarksberg, West Virginia, [REDACTED]",
      "status": "permanent_unresolved",
      "unresolvedReason": "other_documented"
    },
    {
      "lineNumber": 27,
      "text": "and is a person with whom [REDACTED] corresponds concerning",
      "status": "permanent_unresolved",
      "unresolvedReason": "other_documented"
    },
    {
      "lineNumber": 28,
      "text": "flying saucers as [REDACTED] is alleged to have a civilian",
      "status": "permanent_unresolved",
      "unresolvedReason": "other_documented"
    },
    {
      "lineNumber": 29,
      "text": "investigative agency handling investigations",
      "status": "image_matched"
    },
    {
      "lineNumber": 30,
      "text": "concerning flying saucers.",
      "status": "image_matched"
    },
    {
      "lineNumber": 31,
      "status": "blank"
    },
    {
      "lineNumber": 32,
      "text": "[REDACTED] related that he has corresponded with various",
      "status": "permanent_unresolved",
      "unresolvedReason": "other_documented"
    },
    {
      "lineNumber": 33,
      "text": "harbor masters and the U. S. Navy relative to the",
      "status": "image_matched"
    },
    {
      "lineNumber": 34,
      "text": "\"dreadful underground menace which relates to the",
      "status": "image_matched"
    },
    {
      "lineNumber": 35,
      "text": "disappearance of crew and passengers of various ships",
      "status": "image_matched"
    },
    {
      "lineNumber": 36,
      "text": "found floundering in the open seas out of control.\"",
      "status": "image_matched"
    },
    {
      "lineNumber": 37,
      "text": "He stated that [REDACTED] has also shown interest in this",
      "status": "permanent_unresolved",
      "unresolvedReason": "other_documented"
    },
    {
      "lineNumber": 38,
      "text": "subject matter, however, was unable to furnish any",
      "status": "image_matched"
    },
    {
      "lineNumber": 39,
      "text": "further amplifying details. The [REDACTED] is",
      "status": "permanent_unresolved",
      "unresolvedReason": "other_documented"
    },
    {
      "lineNumber": 40,
      "text": "related in the book published by [REDACTED]",
      "status": "permanent_unresolved",
      "unresolvedReason": "other_documented"
    },
    {
      "lineNumber": 41,
      "text": "REC'D",
      "status": "image_matched"
    },
    {
      "lineNumber": 42,
      "text": "2 - Bureau (AM)",
      "status": "image_matched"
    },
    {
      "lineNumber": 43,
      "text": "1 - Phoenix J.O.",
      "status": "image_matched"
    },
    {
      "lineNumber": 44,
      "text": "WMD/mdc",
      "status": "image_matched"
    },
    {
      "lineNumber": 45,
      "text": "(3)",
      "status": "image_matched"
    },
    {
      "lineNumber": 46,
      "text": "EX-108",
      "status": "image_matched"
    },
    {
      "lineNumber": 47,
      "text": "[unclear]",
      "status": "permanent_unresolved",
      "unresolvedReason": "other_documented"
    },
    {
      "lineNumber": 48,
      "text": "29 NOV 1964",
      "status": "image_matched"
    }
  ],
  "blockCount": null
}
